ipclick/__init__.py
ipclick/__main__.py
ipclick/adapters/__init__.py
ipclick/adapters/base.py
ipclick/adapters/curl_cffi_adapter.py
ipclick/adapters/httpx_adapter.py
ipclick/adapters/registry.py
ipclick/cli/__init__.py
ipclick/cli/main.py
ipclick/config_loader/__init__.py
ipclick/config_loader/loader.py
ipclick/configs/__init__.py
ipclick/configs/default_config.toml
ipclick/dto/__init__.py
ipclick/dto/models.py
ipclick/dto/proto/__init__.py
ipclick/dto/proto/task.proto
ipclick/dto/proto/task_pb2.py
ipclick/dto/proto/task_pb2.pyi
ipclick/dto/proto/task_pb2_grpc.py
ipclick/dto/response.py
ipclick/sdk.py
ipclick/server.py
ipclick/services/__init__.py
ipclick/services/task_service.py
ipclick/utils/__init__.py
ipclick/utils/config_util.py
ipclick/utils/log_util.py
ipclick/utils/path_util.py
ipclick/utils/secure_util.py
ipclick-0.1.2.dist-info/entry_points.txt
ipclick-0.1.2.dist-info/licenses/LICENSE
ipclick-0.1.2.dist-info/METADATA
ipclick-0.1.2.dist-info/WHEEL
ipclick-0.1.2.dist-info/RECORD
