Metadata-Version: 2.4
Name: ipclick
Version: 0.1.2
Summary: IPClick Tool
License: MIT
License-File: LICENSE
Author: 元气码农少女酱
Author-email: 1276162429@qq.com
Requires-Python: >=3.11
Classifier: License :: OSI Approved :: MIT License
Classifier: Programming Language :: Python :: 3
Classifier: Programming Language :: Python :: 3.11
Classifier: Programming Language :: Python :: 3.12
Classifier: Programming Language :: Python :: 3.13
Classifier: Programming Language :: Python :: 3.14
Requires-Dist: click (>=8.3.1,<9.0.0)
Requires-Dist: curl-cffi (>=0.14.0,<0.15.0)
Requires-Dist: fake-useragent (>=2.2.0,<3.0.0)
Requires-Dist: grpcio (>=1.76.0,<2.0.0)
Requires-Dist: httpx (>=0.28.1,<0.29.0)
Requires-Dist: loguru (>=0.7.3)
Requires-Dist: protobuf (>=6.33.2,<7.0.0)
Requires-Dist: pydantic (>=2.12.5)
Requires-Dist: python-box[all] (>=7.0,<8.0)
Project-URL: Bug Tracker, https://github.com/yuanqimanong/IPClick/issues
Project-URL: Homepage, https://github.com/yuanqimanong/IPClick
Project-URL: Repository, https://github.com/yuanqimanong/IPClick
